AUTHORS
LICENSE
MANIFEST.in
README.md
setup.py
djangocms_hubspot/__init__.py
djangocms_hubspot/admin.py
djangocms_hubspot/apps.py
djangocms_hubspot/cms_plugins.py
djangocms_hubspot/forms.py
djangocms_hubspot/models.py
djangocms_hubspot.egg-info/PKG-INFO
djangocms_hubspot.egg-info/SOURCES.txt
djangocms_hubspot.egg-info/dependency_links.txt
djangocms_hubspot.egg-info/not-zip-safe
djangocms_hubspot.egg-info/requires.txt
djangocms_hubspot.egg-info/top_level.txt
djangocms_hubspot/migrations/0001_initial.py
djangocms_hubspot/migrations/__init__.py
djangocms_hubspot/templates/djangocms_hubspot/plugins/cta.html
djangocms_hubspot/templates/djangocms_hubspot/plugins/form.html